{
  "version": "7",
  "dialect": "sqlite",
  "entries": [
    {
      "idx": 0,
      "version": "6",
      "when": 1776535716359,
      "tag": "0000_stiff_pride",
      "breakpoints": true
    },
    {
      "idx": 1,
      "version": "6",
      "when": 1776552410093,
      "tag": "0001_steady_mother_askani",
      "breakpoints": true
    },
    {
      "idx": 2,
      "version": "6",
      "when": 1776552515070,
      "tag": "0002_dear_corsair",
      "breakpoints": true
    },
    {
      "idx": 3,
      "version": "6",
      "when": 1776567308718,
      "tag": "0003_chilly_owl",
      "breakpoints": true
    },
    {
      "idx": 4,
      "version": "6",
      "when": 1776599895811,
      "tag": "0004_dashing_bucky",
      "breakpoints": true
    },
    {
      "idx": 5,
      "version": "6",
      "when": 1776601126488,
      "tag": "0005_optimal_scream",
      "breakpoints": true
    },
    {
      "idx": 6,
      "version": "6",
      "when": 1776613427048,
      "tag": "0006_nifty_union_jack",
      "breakpoints": true
    },
    {
      "idx": 7,
      "version": "6",
      "when": 1776616670727,
      "tag": "0007_talented_prima",
      "breakpoints": true
    },
    {
      "idx": 8,
      "version": "6",
      "when": 1776619047904,
      "tag": "0008_tearful_pixie",
      "breakpoints": true
    },
    {
      "idx": 9,
      "version": "6",
      "when": 1776625317183,
      "tag": "0009_slow_wild_child",
      "breakpoints": true
    },
    {
      "idx": 10,
      "version": "6",
      "when": 1776625471153,
      "tag": "0010_bored_umar",
      "breakpoints": true
    },
    {
      "idx": 11,
      "version": "6",
      "when": 1776712585812,
      "tag": "0011_yummy_valkyrie",
      "breakpoints": true
    },
    {
      "idx": 12,
      "version": "6",
      "when": 1745280000000,
      "tag": "0012_agent_improvements",
      "breakpoints": true
    },
    {
      "idx": 13,
      "version": "6",
      "when": 1745280001000,
      "tag": "0013_monitor_groups",
      "breakpoints": true
    },
    {
      "idx": 14,
      "version": "6",
      "when": 1745280002000,
      "tag": "0014_alerts_improvements",
      "breakpoints": true
    },
    {
      "idx": 15,
      "version": "6",
      "when": 1745366400000,
      "tag": "0015_settings",
      "breakpoints": true
    },
    {
      "idx": 16,
      "version": "6",
      "when": 1776894103475,
      "tag": "0016_cuddly_guardian",
      "breakpoints": true
    },
    {
      "idx": 17,
      "version": "6",
      "when": 1776896581674,
      "tag": "0017_nostalgic_rocket_racer",
      "breakpoints": true
    },
    {
      "idx": 18,
      "version": "6",
      "when": 1745366401000,
      "tag": "0018_perf_and_integrity",
      "breakpoints": true
    },
    {
      "idx": 19,
      "version": "6",
      "when": 1745452800000,
      "tag": "0019_bandwidth_limit_on_runs",
      "breakpoints": true
    }
  ]
}